cqed/__init__.py
cqed/analysis.py
cqed/fitcav.py
cqed/freqjump.py
cqed-2.0.0.dist-info/METADATA
cqed-2.0.0.dist-info/WHEEL
cqed-2.0.0.dist-info/top_level.txt
cqed-2.0.0.dist-info/RECORD
