Metadata-Version: 2.1
Name: cqed
Version: 2.0.0
Summary: Modules for CQED experiments
Home-page: UNKNOWN
Author: Guodong Cui
Author-email: guodong.cui@stonybrook.edu
License: UNKNOWN
Platform: UNKNOWN
Requires-Dist: numpy
Requires-Dist: pandas
Requires-Dist: scipy
Requires-Dist: h5py
Requires-Dist: easygui
Requires-Dist: matplotlib
